python_query/__init__.py
python_query/query.py
python_query/query_cache.py
python_query/query_options.py
python_query/types.py
python_query/utils.py
python_query-0.0.1b3.dist-info/LICENSE
python_query-0.0.1b3.dist-info/METADATA
python_query-0.0.1b3.dist-info/WHEEL
python_query-0.0.1b3.dist-info/top_level.txt
python_query-0.0.1b3.dist-info/RECORD
