Metadata-Version: 2.1
Name: python-query
Version: 0.0.1b3
Summary: Like React Query but for Python
Author-email: Nuno Antunes <afonso.antunes@live.com.pt>
Maintainer-email: Nuno Antunes <afonso.antunes@live.com.pt>
License: GNU GENERAL PUBLIC LICENSE
Project-URL: Github:Repository, https://github.com/dreadster3/python-query.git
Project-URL: Github:Issues, https://github.com/dreadster3/python-query/issues
Keywords: query,react-query,python
Classifier: Development Status :: 1 - Planning
Classifier: Operating System :: MacOS
Classifier: Operating System :: Microsoft :: Windows
Classifier: Operating System :: POSIX
Classifier: Intended Audience :: Developers
Classifier: License :: OSI Approved :: GNU Affero General Public License v3
Classifier: Programming Language :: Python
Classifier: Programming Language :: Python :: 3.11
Classifier: Programming Language :: Python :: 3.12
Requires-Python: >=3.11
License-File: LICENSE
Requires-Dist: nest-asyncio <2.0.0,>=1.6.0
Provides-Extra: dev
Requires-Dist: mypy ; extra == 'dev'
Requires-Dist: flake8 ; extra == 'dev'
Requires-Dist: autopep8 ; extra == 'dev'
Requires-Dist: pytest ; extra == 'dev'
Requires-Dist: pytest-asyncio ; extra == 'dev'
Provides-Extra: lint
Requires-Dist: mypy ; extra == 'lint'
Requires-Dist: flake8 ; extra == 'lint'
Requires-Dist: build ; extra == 'lint'
Provides-Extra: release
Requires-Dist: build ; extra == 'release'
Provides-Extra: test
Requires-Dist: pytest ; extra == 'test'
Requires-Dist: pytest-asyncio ; extra == 'test'
Requires-Dist: pytest-cov ; extra == 'test'
Requires-Dist: coverage ; extra == 'test'
